.hgignore
.hgtags
LICENSE
Makefile
README
README.md
setup.py
tox.ini
benchmarks/xattrs.py
example_repo/README
example_repo/environ.yml
example_repo/fission.cfg
example_repo/hosts.yml
example_repo/inventory
example_repo/jobs/job1.node
example_repo/jobs/job1.yml
example_repo/jobs/multi-job/1.extras
example_repo/jobs/multi-job/1.yml
example_repo/jobs/multi-job/2.yml
example_repo/jobs/multi-job/3.yml
example_repo/jobs/multi-job/4.yml
example_repo/jobs/multi-job/README
example_repo/jobs/multi-job/job-template
example_repo/nodes/default
example_repo/nodes/environ.yml
example_repo/nodes/dc1/environ.yml
example_repo/nodes/dc1/hosts.yml
example_repo/nodes/dc1/rack37/blank.yml
example_repo/nodes/dc1/rack37/host1.yml
example_repo/nodes/dc1/rack37/tags.yml
example_repo/scripts/add_host
fission/__init__.py
fission/cli.py
fission/exit_codes.py
fission/repo.py
fission/tags.py
fission/utils.py
fission/verify.py
fission.egg-info/PKG-INFO
fission.egg-info/SOURCES.txt
fission.egg-info/dependency_links.txt
fission.egg-info/entry_points.txt
fission.egg-info/requires.txt
fission.egg-info/top_level.txt
fission.egg-info/zip-safe