Metadata-Version: 1.1
Name: fission
Version: 0.1
Summary: Container managment software
Home-page: http://blitz.works
Author: Da_Blitz
Author-email: code@pocketnix.org
License: MIT BSD
Download-URL: http://blitz.works/fission
Keywords: container
Platform: UNKNOWN
